{
  "defaultCp": 180,

  "================================================== Materias ==================================================": {},
  "cra1": {
    "name": "장인의 마테리아",
    "shortName": "장인아",
    "iconSrc": "/icons/items/craftsmans-competence-materia-i.png",
    "cra": 3
  },
  "cra2": {
    "name": "장인의 마테리라",
    "shortName": "장인라",
    "cra": 4
  },
  "cra3": {
    "name": "장인의 마테리다",
    "shortName": "장인다",
    "cra": 5
  },
  "cra4": {
    "name": "장인의 마테리가",
    "shortName": "장인가",
    "cra": 6
  },
  "cra5": {
    "name": "장인의 마테리쟈",
    "shortName": "장인쟈",
    "cra": 11
  },
  "cra6": {
    "name": "장인의 하이마테리쟈",
    "shortName": "장인하이쟈",
    "description": "작업 숙련도 +16",
    "iconSrc": "/icons/items/craftsmans-competence-materia-vi.png",
    "cra": 16
  },
  "cra7": {
    "name": "장인의 메가마테리쟈",
    "shortName": "장인메가쟈",
    "description": "작업 숙련도 +14",
    "iconSrc": "/icons/items/craftsmans-competence-materia-vii.png",
    "cra": 14
  },
  "cra8": {
    "name": "장인의 엑스마테리쟈",
    "shortName": "장인엑스쟈",
    "description": "작업 숙련도 +21",
    "iconSrc": "/icons/items/craftsmans-competence-materia-viii.png",
    "cra": 21
  },

  "con1": {
    "name": "거장의 마테리아",
    "shortName": "거장아",
    "con": 1
  },
  "con2": {
    "name": "거장의 마테리라",
    "shortName": "거장라",
    "con": 2
  },
  "con3": {
    "name": "거장의 마테리다",
    "shortName": "거장다",
    "con": 3
  },
  "con4": {
    "name": "거장의 마테리가",
    "shortName": "거장가",
    "description": "가공 숙련도 +4",
    "iconSrc": "/icons/items/craftsmans-command-materia-iv.png",
    "con": 4
  },
  "con5": {
    "name": "거장의 마테리쟈",
    "shortName": "거장쟈",
    "con": 7
  },
  "con6": {
    "name": "거장의 하이마테리쟈",
    "shortName": "거장하이쟈",
    "description": "가공 숙련도 +10",
    "iconSrc": "/icons/items/craftsmans-command-materia-vi.png",
    "con": 10
  },
  "con7": {
    "name": "거장의 메가마테리쟈",
    "shortName": "거장메가쟈",
    "description": "가공 숙련도 +9",
    "iconSrc": "/icons/items/craftsmans-command-materia-vii.png",
    "con": 9
  },
  "con8": {
    "name": "거장의 엑스마테리쟈",
    "shortName": "거장엑스쟈",
    "description": "가공 숙련도 +13",
    "iconSrc": "/icons/items/craftsmans-command-materia-viii.png",
    "con": 13
  },

  "cp1": {
    "name": "명인의 마테리아",
    "shortName": "명인아",
    "description": "CP +1",
    "iconSrc": "/icons/items/craftsmans-cunning-materia-i.png",
    "cp": 1
  },
  "cp2": {
    "name": "명인의 마테리라",
    "shortName": "명인라",
    "description": "CP +2",
    "iconSrc": "/icons/items/craftsmans-cunning-materia-ii.png",
    "cp": 2
  },
  "cp3": {
    "name": "명인의 마테리다",
    "shortName": "명인다",
    "description": "CP +3",
    "iconSrc": "/icons/items/craftsmans-cunning-materia-iii.png",
    "cp": 3
  },
  "cp4": {
    "name": "명인의 마테리가",
    "shortName": "명인가",
    "description": "CP +4",
    "iconSrc": "/icons/items/craftsmans-cunning-materia-iv.png",
    "cp": 4
  },
  "cp5": {
    "name": "명인의 마테리쟈",
    "shortName": "명인쟈",
    "description": "CP +6",
    "iconSrc": "/icons/items/craftsmans-cunning-materia-v.png",
    "cp": 6
  },
  "cp6": {
    "name": "명인의 하이마테리쟈",
    "shortName": "명인하이쟈",
    "description": "CP +8",
    "iconSrc": "/icons/items/craftsmans-cunning-materia-vi.png",
    "cp": 8
  },
  "cp7": {
    "name": "명인의 메가마테리쟈",
    "shortName": "명인메가쟈",
    "cp": 7
  },
  "cp8": {
    "name": "명인의 엑스마테리쟈",
    "shortName": "명인엑스쟈",
    "cp": 9
  },

  "================================================== 290 Gears ==================================================": {},
  "================================================== 290 Earrings ==================================================": {},
  "zelkovaEarrings": {
    "name": "느티나무 귀걸이",
    "iconSrc": "/icons/items/zelkova-earrings.png",
    "itemLevel": 290,
    "cra": 6,
    "cp": 41
  },
  "================================================== 290 Necklace ==================================================": {},
  "zelkovaNecklace": {
    "name": "느티나무 목걸이",
    "iconSrc": "/icons/items/zelkova-necklace.png",
    "itemLevel": 290,
    "cra": 6,
    "cp": 41
  },
  "================================================== 290 Bracelets ==================================================": {},
  "zelkovaBracelets": {
    "name": "느티나무 팔찌",
    "iconSrc": "/icons/items/zelkova-bracelets.png",
    "itemLevel": 290,
    "cra": 6,
    "cp": 41
  },
  "================================================== 290 Rings ==================================================": {},
  "zelkovaRing": {
    "name": "느티나무 반지",
    "iconSrc": "/icons/items/zelkova-ring.png",
    "itemLevel": 290,
    "con": 12,
    "cp": 21
  },

  "================================================== 430 Gears ==================================================": {},
  "================================================== 430 Primary ==================================================": {},
  "dwarvenMythrilSaw": {
    "name": "디미스라이트 톱",
    "iconSrc": "/icons/items/dwarven-mythril-saw.png",
    "itemLevel": 430,
    "cra": 580,
    "con": 314,
    "hq": {
      "iconSrc": "/icons/items/hq/dwarven-mythril-saw.png",
      "cra": 657,
      "con": 356
    }
  },
  "================================================== 430 Secondary ==================================================": {},
  "dwarvenMythrilClawHammer": {
    "name": "디미스라이트 장도리",
    "iconSrc": "/icons/items/dwarven-mythril-claw-hammer.png",
    "itemLevel": 430,
    "cra": 580,
    "con": 314,
    "hq": {
      "iconSrc": "/icons/items/hq/dwarven-mythril-claw-hammer.png",
      "cra": 657,
      "con": 356
    }
  },
  "================================================== 430 Head ==================================================": {},
  "dwarvenCottonBeret": {
    "name": "드워프 무명 베레모",
    "iconSrc": "/icons/items/dwarven-cotton-beret.png",
    "itemLevel": 430,
    "con": 157,
    "cp": 7,
    "hq": {
      "iconSrc": "/icons/items/hq/dwarven-cotton-beret.png",
      "con": 178,
      "cp": 7
    }
  },
  "================================================== 430 Body ==================================================": {},
  "dwarvenCottonJacket": {
    "name": "드워프 무명 재킷",
    "iconSrc": "/icons/items/dwarven-cotton-jacket.png",
    "itemLevel": 430,
    "cra": 497,
    "con": 157,
    "cp": 4,
    "hq": {
      "iconSrc": "/icons/items/hq/dwarven-cotton-jacket.png",
      "cra": 563,
      "con": 178,
      "cp": 5
    }
  },
  "================================================== 430 Hands ==================================================": {},
  "swallowskinFingerlessGloves": {
    "name": "바다제비 반장갑",
    "iconSrc": "/icons/items/swallowskin-fingerless-gloves.png",
    "itemLevel": 430,
    "con": 157,
    "cp": 7,
    "hq": {
      "iconSrc": "/icons/items/hq/swallowskin-fingerless-gloves.png",
      "con": 178,
      "cp": 7
    }
  },
  "================================================== 430 Waist ==================================================": {},
  "swallowskinToolBelt": {
    "name": "바다제비 공구 허리띠",
    "iconSrc": "/icons/items/swallowskin-tool-belt.png",
    "itemLevel": 430,
    "con": 157,
    "hq": {
      "iconSrc": "/icons/items/hq/swallowskin-tool-belt.png",
      "con": 178
    }
  },
  "================================================== 430 Legs ==================================================": {},
  "dwarvenCottonTrousers": {
    "name": "드워프 무명 긴바지",
    "iconSrc": "/icons/items/dwarven-cotton-trousers.png",
    "itemLevel": 430,
    "cra": 33,
    "con": 157,
    "hq": {
      "iconSrc": "/icons/items/hq/dwarven-cotton-trousers.png",
      "cra": 38,
      "con": 178
    }
  },
  "================================================== 430 Feet ==================================================": {},
  "swallowskinShoes": {
    "name": "바다제비 신발",
    "iconSrc": "/icons/items/swallowskin-shoes.png",
    "itemLevel": 430,
    "cra": 33,
    "con": 157,
    "hq": {
      "iconSrc": "/icons/items/hq/swallowskin-shoes.png",
      "cra": 38,
      "con": 178
    }
  },
  "================================================== 430 Earrings ==================================================": {},
  "dwarvenMythrilEarCuffs": {
    "name": "디미스라이트 귀찌",
    "iconSrc": "/icons/items/dwarven-mythril-ear-cuffs.png",
    "itemLevel": 430,
    "cra": 33,
    "cp": 55,
    "hq": {
      "iconSrc": "/icons/items/hq/dwarven-mythril-ear-cuffs.png",
      "cra": 38,
      "cp": 62
    }
  },
  "================================================== 430 Necklace ==================================================": {},
  "dwarvenMythrilChoker": {
    "name": "디미스라이트 목장식",
    "iconSrc": "/icons/items/dwarven-mythril-choker.png",
    "itemLevel": 430,
    "cra": 33,
    "cp": 55,
    "hq": {
      "iconSrc": "/icons/items/hq/dwarven-mythril-choker.png",
      "cra": 38,
      "cp": 62
    }
  },
  "================================================== 430 Bracelets ==================================================": {},
  "dwarvenMythrilBracelets": {
    "name": "디미스라이트 팔찌",
    "iconSrc": "/icons/items/dwarven-mythril-bracelets.png",
    "itemLevel": 430,
    "cra": 33,
    "cp": 55,
    "hq": {
      "iconSrc": "/icons/items/hq/dwarven-mythril-bracelets.png",
      "cra": 38,
      "cp": 62
    }
  },
  "================================================== 430 Ring ==================================================": {},
  "dwarvenMythrilRing": {
    "name": "디미스라이트 반지",
    "iconSrc": "/icons/items/dwarven-mythril-ring.png",
    "itemLevel": 430,
    "con": 63,
    "cp": 29,
    "hq": {
      "iconSrc": "/icons/items/hq/dwarven-mythril-ring.png",
      "con": 71,
      "cp": 32
    }
  }
}
